python_ottawa_transit/__init__.py
python_ottawa_transit/api.py
python_ottawa_transit-0.2.0.dist-info/WHEEL
python_ottawa_transit-0.2.0.dist-info/METADATA
python_ottawa_transit-0.2.0.dist-info/RECORD
