Metadata-Version: 2.1
Name: python-ottawa-transit
Version: 0.2.0
Summary: Python interface for OCTranspo API
Home-page: https://github.com/buckley-w-david/python-ottawa-transit
License: MIT
Author: David Buckley
Author-email: buckley.w.david@gmail.com
Requires-Python: >=3.6,<4.0
Classifier: License :: OSI Approved :: MIT License
Classifier: Programming Language :: Python :: 3
Classifier: Programming Language :: Python :: 3.6
Classifier: Programming Language :: Python :: 3.7
